pdf2docx_rg/__init__.py
pdf2docx_rg/converter.py
pdf2docx_rg/main.py
pdf2docx_rg/common/Block.py
pdf2docx_rg/common/Collection.py
pdf2docx_rg/common/Element.py
pdf2docx_rg/common/__init__.py
pdf2docx_rg/common/constants.py
pdf2docx_rg/common/docx.py
pdf2docx_rg/common/share.py
pdf2docx_rg/font/Fonts.py
pdf2docx_rg/font/__init__.py
pdf2docx_rg/image/Image.py
pdf2docx_rg/image/ImageBlock.py
pdf2docx_rg/image/ImageSpan.py
pdf2docx_rg/image/ImagesExtractor.py
pdf2docx_rg/image/__init__.py
pdf2docx_rg/layout/Blocks.py
pdf2docx_rg/layout/Column.py
pdf2docx_rg/layout/Layout.py
pdf2docx_rg/layout/Section.py
pdf2docx_rg/layout/Sections.py
pdf2docx_rg/layout/__init__.py
pdf2docx_rg/page/BasePage.py
pdf2docx_rg/page/Page.py
pdf2docx_rg/page/Pages.py
pdf2docx_rg/page/RawPage.py
pdf2docx_rg/page/__init__.py
pdf2docx_rg/shape/Path.py
pdf2docx_rg/shape/Paths.py
pdf2docx_rg/shape/Shape.py
pdf2docx_rg/shape/Shapes.py
pdf2docx_rg/shape/__init__.py
pdf2docx_rg/table/Border.py
pdf2docx_rg/table/Cell.py
pdf2docx_rg/table/Cells.py
pdf2docx_rg/table/Row.py
pdf2docx_rg/table/Rows.py
pdf2docx_rg/table/TableBlock.py
pdf2docx_rg/table/TableStructure.py
pdf2docx_rg/table/TablesConstructor.py
pdf2docx_rg/table/__init__.py
pdf2docx_rg/text/Char.py
pdf2docx_rg/text/Line.py
pdf2docx_rg/text/Lines.py
pdf2docx_rg/text/Spans.py
pdf2docx_rg/text/TextBlock.py
pdf2docx_rg/text/TextSpan.py
pdf2docx_rg/text/__init__.py
pdf2docx_rg-0.1.dist-info/LICENSE
pdf2docx_rg-0.1.dist-info/METADATA
pdf2docx_rg-0.1.dist-info/WHEEL
pdf2docx_rg-0.1.dist-info/entry_points.txt
pdf2docx_rg-0.1.dist-info/top_level.txt
pdf2docx_rg-0.1.dist-info/RECORD
