Metadata-Version: 2.1
Name: pdf2docx-rg
Version: 0.1
Summary: parse PDF files to docx
Home-page: https://github.com/dothinking/pdf2docx_rg
Author: dothinking
Author-email: train8808@gmail.com
License: GPL v3
Keywords: pdf-to-word,pdf-to-docx
Platform: UNKNOWN
Requires-Python: >=3.6
Requires-Dist: PyMuPDF (>=1.19.0)
Requires-Dist: python-docx (>=0.8.10)
Requires-Dist: fonttools (>=4.24.0)
Requires-Dist: numpy (>=1.17.2)
Requires-Dist: opencv-python (>=4.5)
Requires-Dist: fire (>=0.3.0)
